[
  {
    "type": "initial",
    "type_id": "initial_name",
    "priority": 1,
    "emoji": "🙋🏻",
    "emoji_note": "happy person raising one hand",
    "solo": true,
    "skip": false,
    "name": "Имя",
    "rules": "Укажи имя, которое увидят другие игроки",
    "score": 5
  },
  {
    "type": "initial",
    "type_id": "initial_selfie",
    "priority": 2,
    "emoji": "📷",
    "emoji_note": "camera",
    "solo": true,
    "skip": true,
    "name": "Селфи",
    "rules": "Сделай селфи, чтобы другим игрокам было легче тебя узнать",
    "score": 10
  },
  {
    "type": "initial",
    "type_id": "initial_phone",
    "priority": 3,
    "emoji": "📱",
    "emoji_note": "mobile_phone",
    "solo": true,
    "skip": true,
    "name": "Телефон",
    "rules": "Укажи телефон, чтобы другие игроки могли тебе позвонить",
    "score": 10
  },
  {
    "type": "initial",
    "type_id": "initial_telegram",
    "priority": 4,
    "solo": true,
    "skip": true,
    "name": "Телеграм",
    "rules": "Укажи ссылку на профиль в Телеграме, чтобы другие игроки могли тебе написать",
    "score": 5
  },
  {
    "type": "regular",
    "type_id": "regular_tic-tac-toe",
    "emoji": "❌⭕️",
    "emoji_note": "cross mark + heavy large circle",
    "solo": false,
    "skip": true,
    "name": "Крестики-нолики",
    "rules": "Сыграйте пять партий в крестики-нолики. В случае ничьей по партиям определите победителя с помощью камня, ножниц и бумаги",
    "score": 10
  },
  {
    "type": "regular",
    "type_id": "regular_balance",
    "solo": false,
    "skip": true,
    "name": "Баланс",
    "rules": "Кто дольше простоит на балансборде, тот и победил. Балансборд — около кофепоинта",
    "score": 10
  },
  {
    "type": "regular",
    "type_id": "regular_1k-run",
    "emoji": "🏃🏻",
    "emoji_note": "runner",
    "solo": false,
    "skip": true,
    "name": "Забег на 1 километр",
    "rules": "Кто быстрее пробежит 1 километр, тот и победил",
    "score": 20
  },
  {
    "type": "regular",
    "type_id": "regular_drink-water",
    "emoji": "🍷",
    "emoji_note": "wine glass",
    "solo": false,
    "skip": true,
    "name": "Полтора литра",
    "rules": "Кто быстрее выпьет 1,5 литра воды, тот и победил",
    "score": 15
  },
  {
    "type": "regular",
    "type_id": "regular_cities",
    "emoji": "🏙",
    "emoji_note": "cityscape",
    "solo": false,
    "skip": true,
    "name": "Города",
    "rules": "Играйте в «Города». Кто замолчит больше, чем на секунды — проиграл",
    "score": 15
  }
]